Workbook

Sheet Costos Personal
A1: Cargo | B1: Cantidad | C1: Salario Base Mensual | D1: Auxilio Transporte | E1: Prestaciones (40%) | F1: salud + pension empleado | G1: Costo Total Mensual | H1: Costo Total Anual
A2: Líder Técnico Junior | B2: 1 | C2: 7000000 | D2: 0 | E2: =SUM(B16:B21) -> 2340471 | F2: =+SUM(B24:B25) -> 560000 | G2: =+C2+D2+E2+-F2 -> 8780471 | H2: =+G2*12 -> 105365652
A3: Desarrollador Junior | B3: 1 | C3: 2750395 | D3: 249605 | E3: =+SUM(C16:C21) -> 961394.93 | F3: =+SUM(C24:C25) -> 220031.6 | G3: =+C3+D3+E3-F3 -> 3741363.3 | H3: =+G3*12 -> 44896360
A4: Desarrollador Junior | B4: 1 | C4: 2750395 | D4: 249605 | E4: =+SUM(D16:D21) -> 961394.93 | F4: =+SUM(D24:D25) -> 220031.6 | G4: =+C4+D4+E4-F4 -> 3741363.3 | H4: =+G4*12 -> 44896360
A5: Testing | B5: 1 | C5: 1750905 | D5: 249605 | E5: =+SUM(E16:E21) -> 627212.45 | F5: =+SUM(E24:E25) -> 140072.4 | G5: =+C5+D5+E5-F5 -> 2487650.1 | H5: =+G5*12 -> 29851801
G6: =SUM(G2:G5) -> 18750848 | H6: =+SUM(H2:H5) -> 2.2501017e+08
B12: Lider tecnico | C12: Desarrollador Junior | D12: Desarrollador Junior | E12: Testing
A13: salario base | B13: =+C2 -> 7000000 | C13: =+C3 -> 2750395 | D13: =+C4 -> 2750395 | E13: =+C5 -> 1750905
A14: auxilio de trasnporte | B14: 0 | C14: 249605 | D14: 249605 | E14: 249605
A15: salario base | B15: =+SUM(B13:B14) -> 7000000 | C15: =+SUM(C13:C14) -> 3000000 | D15: =+SUM(D13:D14) -> 3000000 | E15: =+SUM(E13:E14) -> 2000510
A16: pension 12% | B16: =+B13*12% -> 840000 | C16: =+C13*12% -> 330047.4 | D16: =+D13*12% -> 330047.4 | E16: =+E13*12% -> 210108.6
A17: ARL 0.52% | B17: =+B13 * 0.522% -> 36540 | C17: =+C13 * 0.522% -> 14357.062 | D17: =+D13 * 0.522% -> 14357.062 | E17: =+E13 * 0.522% -> 9139.7241
A18: Prima 8.33% | B18: =+B15*8.33% -> 583100 | C18: =+C15*8.33% -> 249900 | D18: =+D15*8.33% -> 249900 | E18: =+E15*8.33% -> 166642.48
A19: Censatias 8.33% | B19: =+B15*8.33% -> 583100 | C19: =+C15*8.33% -> 249900 | D19: =+D15*8.33% -> 249900 | E19: =+E15*8.33% -> 166642.48
A20: Interes cesantias 1% | B20: =+B19*1% -> 5831 | C20: =+C19*1% -> 2499 | D20: =+D19*1% -> 2499 | E20: =+E19*1% -> 1666.4248
A21: Vacaciones 4.17% | B21: =+B13*4.17% -> 291900 | C21: =+C13*4.17% -> 114691.47 | D21: =+D13*4.17% -> 114691.47 | E21: =+E13*4.17% -> 73012.739
A22: Total | B22: =+SUM(B15:B21) -> 9340471 | C22: =+SUM(C15:C21) -> 3961394.9 | D22: =+SUM(D15:D21) -> 3961394.9 | E22: =+SUM(E15:E21) -> 2627722.5
A24: salud 4% | B24: =+B13*4% -> 280000 | C24: =+C13*4% -> 110015.8 | D24: =+D13*4% -> 110015.8 | E24: =+E13*4% -> 70036.2
A25: pension 4% | B25: =+B13*4% -> 280000 | C25: =+C13*4% -> 110015.8 | D25: =+D13*4% -> 110015.8 | E25: =+E13*4% -> 70036.2
A27: Total devengado | B27: =+B22-B24-B25 -> 8780471 | C27: =+C22-C24-C25 -> 3741363.3 | D27: =+D22-D24-D25 -> 3741363.3 | E27: =+E22-E24-E25 -> 2487650.1

Sheet Infraestructura
A1: Concepto | B1: Valor Mensual | C1: Valor Anual
A2: Hosting VPS o nube | B2: 180000 | C2: 2160000
A3: Dominio web (.com) | B3: 0 | C3: 70000
A4: Certificado SSL | B4: 0 | C4: 120000
A5: Base de datos cloud | B5: 80000 | C5: 960000
C6: =+SUM(C2:C5) -> 3310000

Sheet Equipos
A1: Equipo | B1: Cantidad | C1: Valor Unitario | D1: Total
A2: Computadores Portátiles | B2: 3 | C2: 3500000 | D2: 10500000
A3: Mouse y periféricos | B3: 3 | C3: 120000 | D3: 360000
A4: UPS o reguladores | B4: 3 | C4: 180000 | D4: 540000
D5: =+SUM(D2:D4) -> 11400000

Sheet Matriz Riesgos
A1: Riesgo | B1: Probabilidad | C1: Impacto | D1: Nivel | E1: Mitigación
A2: Retrasos en el desarrollo | B2: Alta | C2: Alta | D2: Crítico | E2: Uso de metodologías ágiles
A3: Pérdida de información | B3: Media | C3: Alta | D3: Alto | E3: Backups automáticos
A4: Fallas del servidor | B4: Media | C4: Alta | D4: Alto | E4: Hosting con redundancia
A5: Renuncia de un integrante | B5: Baja | C5: Alta | D5: Medio | E5: Documentación constante
A6: Cambios en requisitos | B6: Alta | C6: Media | D6: Alto | E6: Actas de requerimientos
A7: Vulnerabilidades de seguridad | B7: Media | C7: Alta | D7: Alto | E7: Pruebas de seguridad

Sheet PROYECCION
A1: COSTOS Y INGRESOS ANTES DE APLICACIÓN | G1: COSTOS Y INGRESOS DESPUES DE APLICACIÓN
A2: GASTOS SUELDOS | C2: GASTOS ADMINISTRATIVOS | G2: GASTOS SUELDOS | I2: GASTOS ADMINISTRATIVOS
A3: VETERINARIO 1 | B3: 3000000 | C3: ARRIENDO | D3: 5000000 | G3: VETERINARIO 1 | H3: 3000000 | I3: ARRIENDO | J3: 5000000
A4: VETERINARIO 2 | B4: 3000000 | C4: SERVICIOS AGUA + LUZ | D4: 1600000 | G4: VETERINARIO 2 | H4: 3000000 | I4: SERVICIOS AGUA + LUZ (25%) | J4: 2000000
A5: RECEPCIONISTA | B5: 2000000 | C5: PAPELERIA | D5: 200000 | G5: RECEPCIONISTA | H5: 2000000 | I5: PAPELERIA | J5: 0
A6: PELQUERO CANINO | B6: 2500000 | C6: INTERNET | D6: 90000 | G6: PELQUERO CANINO | H6: 2500000 | I6: INTERNET | J6: 112500
A7: N/A | B7: 0 | C7: N/A | D7: 0 | G7: PELUQUERO CANINO | H7: 2500000
A8: TOTAL GASTOS MENSUALES | B8: =+SUM(B3:B6) -> 10500000 | D8: =+SUM(D3:D6) -> 6890000 | G8: TOTAL GASTOS MENSUALES | H8: =+SUM(H3:H7) -> 13000000 | J8: =+SUM(J3:J6) -> 7112500
A9: TOTAL | B9: =+B8+D8 -> 17390000 | G9: TOTAL | H9: =+H8+J8 -> 20112500
A11: INGRESOS SEMANALES ACTUALMENTE | G11: INGRESOS SEMANALES PROYECTADOS
A12: PROFESIONAL | B12: PACIENTES SEMANALES | C12: TOTAL INGRESOS SEMANA | G12: PROFESIONAL | H12: PACIENTES SEMANALES | I12: TOTAL INGRESOS SEMANA
A13: VETERINARIO 1 | B13: 20 | C13: =+B13*B20 -> 1600000 | G13: VETERINARIO 1 | H13: 30 | I13: =+H13*H20 -> 2700000
A14: VETERINARIO2 | B14: 20 | C14: =+B14*B20 -> 1600000 | G14: VETERINARIO 2 | H14: 30 | I14: =+H14*H20 -> 2700000
A15: PELQUERO CANINO | B15: 50 | C15: =+B15*B21 -> 2500000 | G15: PELQUERO CANINO X 2 | H15: 100 | I15: =+H15*H21 -> 6500000
A16: TOTAL SEMANA | B16: =+SUM(B13:B15) -> 90 | C16: =+SUM(C13:C15) -> 5700000 | G16: TOTAL | H16: =+SUM(H13:H15) -> 160 | I16: =+SUM(I13:I15) -> 11900000
A17: INGRESOS MENSUALES | B17: =+C16*4 -> 22800000 | G17: INGRESOS MENSUALES | H17: =+I16*4 -> 47600000
A20: COSTO CONSULTA GENERAL | B20: 80000 | G20: COSTO CONSULTA GENERAL | H20: 90000
A21: COSTO PELUQUERIA | B21: 50000 | G21: COSTO PELUQUERIA | H21: 65000
A23: TOTAL INGRESOS ANUALES | B23: =+B17*12 -> 273600000 | G23: TOTAL INGRESOS ANUALES | H23: =+H17*12 -> 571200000
A24: TOTAL GASTOS ANUALES | B24: =+B9*12 -> 208680000 | G24: TOTAL GASTOS ANUALES | H24: =+H9*12 -> 241350000
A25: UTILIDAD | B25: =+B23-B24 -> 64920000 | G25: UTILIDAD | H25: =+H23-H24 -> 329850000

Sheet TCO
A1: Categoría | B1: Valor
A2: Personal | B2: =+'Costos Personal'!H6 -> 2.2501017e+08
A3: Infraestructura | B3: =+Infraestructura!C6 -> 3310000
A4: Equipos | B4: =+Equipos!D5 -> 11400000
A5: TOTAL GENERAL | B5: =+SUM(B2:B4) -> 2.3972017e+08
A6: Contingecia 10% | B6: =+B5*10% -> 23972017
A7: TOTAL | B7: =+B5+B6 -> 2.6369219e+08
A8: Ganancia 50% | B8: =B7*50% -> 1.3184609e+08
A9: COSTO TOTAL PROYECTO | B9: =+B7+B8 -> 3.9553828e+08
A11: Costo por Trimestre | B11: =+B9/4 -> 98884571

Sheet ROI
A1: ROI - RETORNO DE INVERSIÓN
A3: Concepto | B3: Valor
A4: Ingresos anuales proyectados | B4: 571200000
A5: Gastos anuales proyectados | B5: 241350000
A6: Utilidad anual proyectada | B6: 329850000
A7: Costo total del proyecto | B7: 3.9553828e+08
A8: ROI (%) | B8: =+(B6-B7)/(B7)*100 -> -16.607314

Sheet Diagrama de Gantt
A3: Trimestre | B3: Actividades | C3: Descripción | D3: Inicio estimado | E3: Duración estimada (días hábiles) | F3: Costo Total Trimestre | G3: Total dias Habiles | H3: Fin estimado
A4: Trimestre 1 Analisis y Planeación | B4: Actividad 1 | C4: Nombre del proyecto y alcance | D4: 46132 | E4: 5 | F4: =+TCO!B11 -> 98884571 | G4: 47 | H4: 46136
B5: Actividad 1.2 | C5: Diagrama del proceso actual | D5: 46139 | E5: 4 | H5: 46142
B6: Actividad 1.3 | C6: Recolección y análisis de datos | D6: 46143 | E6: 6 | H6: 46150
B7: Actividad 1.4 | C7: Requerimientos IEEE / Historias de usuario | D7: 46153 | E7: 8 | H7: 46163
B8: Actividad 1.5 | C8: Casos de uso y documentación | D8: 46164 | E8: 7 | H8: 46174
B9: Actividad 1.6 | C9: Mockups y wireframes | D9: 46175 | E9: 6 | H9: 46183
B10: Actividad 1.7 | C10: Estimación de costos e infraestructura | D10: 46184 | E10: 8 | H10: 46196
B11: Actividad 1.8 | C11: Control de versiones inicial | D11: 46195 | E11: 3 | H11: 46197
A12: Trimestre 2 Diseño de Sistema | B12: Actividad 2 | C12: Normalización 3FN | D12: 46198 | E12: 5 | F12: =+TCO!B11 -> 98884571 | G12: 38 | H12: 46205
B13: Actividad 2.2 | C13: Diccionario de datos | D13: 46203 | E13: 5 | H13: 46209
B14: Actividad 2.3 | C14: Modelo relacional | D14: 46206 | E14: 5 | H14: 46212
B15: Actividad 2.4 | C15: Diagrama de clases | D15: 46210 | E15: 5 | H15: 46216
B16: Actividad 2.5 | C16: Diagrama de despliegue | D16: 46213 | E16: 5 | H16: 46219
B17: Actividad 2.6 | C17: Prototipo navegable HTML/CSS | D17: 46217 | E17: 10 | H17: 46231
B18: Actividad 2.7 | C18: Control de versiones y ramas | D18: 46225 | E18: 3 | H18: 46227
A19: Trimestre 3 Desarrollo e Integración | B19: Actividad 3 | C19: Construcción base de datos DDL | D19: 46230 | E19: 8 | F19: =+F12 -> 98884571 | G19: 70 | H19: 46239
B20: Actividad 3.2 | C20: Consultas DML y CRUD | D20: 46233 | E20: 8 | H20: 46244
B21: Actividad 3.3 | C21: Seguridad y cifrado | D21: 46240 | E21: 6 | H21: 46249
B22: Actividad 3.4 | C22: Front-End funcional | D22: 46247 | E22: 15 | H22: 46267
B23: Actividad 3.5 | C23: Control de versiones | D23: 46268 | E23: 3 | H23: 46270
B24: Actividad 3.6 | C24: API REST segura JWT | D24: 46268 | E24: 12 | H24: 46283
B25: Actividad 3.7 | C25: Consumo Front-End API 80% | D25: 46282 | E25: 15 | H25: 46302
B26: Actividad 3.8 | C26: Control de versiones | D26: 46303 | E26: 3 | H26: 46307
A27: Trimestre 4 Prueba y Despliegue | B27: Actividad 4 | C27: Sistema completo 100% | D27: 46308 | E27: 20 | F27: =+F19 -> 98884571 | G27: 88 | H27: 46335
B28: Actividad 4.2 | C28: Aplicación móvil | D28: 46329 | E28: 15 | H28: 46349
B29: Actividad 4.3 | C29: Documentación API | D29: 46350 | E29: 5 | H29: 46356
B30: Actividad 4.4 | C30: Metodología ágil | D30: 46352 | E30: 5 | H30: 46358
B31: Actividad 4.5 | C31: Control de versiones | D31: 46359 | E31: 3 | H31: 46363
B32: Actividad 4.6 | C32: Pruebas de software | D32: 46365 | E32: 10 | H32: 46380
B33: Actividad 4.7 | C33: Plan de instalación y migración | D33: 46378 | E33: 6 | H33: 46385
B34: Actividad 4.8 | C34: Modelo de calidad | D34: 46386 | E34: 5 | H34: 46392
B35: Actividad 4.9 | C35: Manuales técnicos y usuario | D35: 46387 | E35: 8 | H35: 46399
B36: Actividad 4.10 | C36: Despliegue del aplicativo | D36: 46400 | E36: 8 | H36: 46409
B37: Actividad 4.11 | C37: Control de versiones final | D37: 46412 | E37: 3 | H37: 46414
C39: Fecha Inicio | D39: =+MIN(D4:D37) -> 46132
C40: Fecha Final | D40: =+MAX(H4:H37) -> 46414
